{
	"type": "FeatureCollection",
	"features": [
		{
			"type": "Feature",
			"geometry": {
				"type": "Polygon",
				"coordinates": [
					[
						[
							111.36455,
							39.45303
						],
						[
							111.40739,
							39.45156
						],
						[
							111.41825,
							39.44514
						],
						[
							111.42082,
							39.43814
						],
						[
							111.418,
							39.41966
						],
						[
							111.4276,
							39.39735
						],
						[
							111.44461,
							39.39164
						],
						[
							111.4525,
							39.38462
						],
						[
							111.45178,
							39.37816
						],
						[
							111.4489,
							39.373
						],
						[
							111.43952,
							39.36342
						],
						[
							111.43556,
							39.3566
						],
						[
							111.42452,
							39.34947
						],
						[
							111.42079,
							39.34358
						],
						[
							111.4177,
							39.33702
						],
						[
							111.41869,
							39.33155
						],
						[
							111.42367,
							39.32395
						],
						[
							111.46475,
							39.308
						],
						[
							111.47317,
							39.30168
						],
						[
							111.48781,
							39.2784
						],
						[
							111.49692,
							39.27464
						],
						[
							111.51778,
							39.2718
						],
						[
							111.53036,
							39.26472
						],
						[
							111.53381,
							39.25774
						],
						[
							111.53898,
							39.25129
						],
						[
							111.55178,
							39.24974
						],
						[
							111.57958,
							39.25339
						],
						[
							111.59327,
							39.25292
						],
						[
							111.60504,
							39.24655
						],
						[
							111.61409,
							39.24375
						],
						[
							111.61519,
							39.23848
						],
						[
							111.61372,
							39.22264
						],
						[
							111.61629,
							39.21892
						],
						[
							111.61896,
							39.21813
						],
						[
							111.60969,
							39.21482
						],
						[
							111.60154,
							39.20973
						],
						[
							111.60238,
							39.20233
						],
						[
							111.59533,
							39.19523
						],
						[
							111.58094,
							39.1872
						],
						[
							111.55252,
							39.17416
						],
						[
							111.54785,
							39.17374
						],
						[
							111.53443,
							39.18269
						],
						[
							111.52753,
							39.18322
						],
						[
							111.52352,
							39.18144
						],
						[
							111.51872,
							39.1774
						],
						[
							111.51794,
							39.17511
						],
						[
							111.52111,
							39.16776
						],
						[
							111.51847,
							39.1643
						],
						[
							111.50873,
							39.1556
						],
						[
							111.49638,
							39.1492
						],
						[
							111.49019,
							39.14276
						],
						[
							111.48953,
							39.13675
						],
						[
							111.49222,
							39.12955
						],
						[
							111.50601,
							39.11953
						],
						[
							111.50638,
							39.11535
						],
						[
							111.50449,
							39.10616
						],
						[
							111.49677,
							39.10081
						],
						[
							111.49491,
							39.09781
						],
						[
							111.49271,
							39.09098
						],
						[
							111.49267,
							39.08076
						],
						[
							111.48471,
							39.0707
						],
						[
							111.48151,
							39.05944
						],
						[
							111.4818,
							39.05341
						],
						[
							111.48462,
							39.04758
						],
						[
							111.48352,
							39.02549
						],
						[
							111.4866,
							39.00679
						],
						[
							111.4889,
							39.00334
						],
						[
							111.499,
							39.00122
						],
						[
							111.50079,
							38.99341
						],
						[
							111.49716,
							38.98955
						],
						[
							111.4934,
							38.99286
						],
						[
							111.4886,
							38.98964
						],
						[
							111.484,
							38.98909
						],
						[
							111.4816,
							38.98592
						],
						[
							111.47373,
							38.98078
						],
						[
							111.46534,
							38.97883
						],
						[
							111.46143,
							38.97592
						],
						[
							111.45033,
							38.97477
						],
						[
							111.42418,
							38.96562
						],
						[
							111.41278,
							38.96008
						],
						[
							111.40298,
							38.95276
						],
						[
							111.39587,
							38.94073
						],
						[
							111.39394,
							38.93468
						],
						[
							111.39424,
							38.92642
						],
						[
							111.40661,
							38.90217
						],
						[
							111.39248,
							38.90591
						],
						[
							111.37412,
							38.91473
						],
						[
							111.36689,
							38.9167
						],
						[
							111.34125,
							38.91965
						],
						[
							111.32709,
							38.91946
						],
						[
							111.31519,
							38.91638
						],
						[
							111.31035,
							38.92603
						],
						[
							111.31133,
							38.9345
						],
						[
							111.31802,
							38.94417
						],
						[
							111.31984,
							38.94905
						],
						[
							111.32467,
							38.95251
						],
						[
							111.33061,
							38.95461
						],
						[
							111.33543,
							38.95962
						],
						[
							111.33563,
							38.9638
						],
						[
							111.3257,
							38.97647
						],
						[
							111.3238,
							38.98712
						],
						[
							111.31449,
							38.99498
						],
						[
							111.31403,
							38.99796
						],
						[
							111.30789,
							39.00318
						],
						[
							111.302,
							39.00579
						],
						[
							111.27389,
							39.01203
						],
						[
							111.27127,
							39.01445
						],
						[
							111.27842,
							39.0224
						],
						[
							111.28078,
							39.03337
						],
						[
							111.2753,
							39.04414
						],
						[
							111.27078,
							39.04821
						],
						[
							111.25658,
							39.05595
						],
						[
							111.25396,
							39.05861
						],
						[
							111.24959,
							39.06061
						],
						[
							111.24246,
							39.06162
						],
						[
							111.23633,
							39.06893
						],
						[
							111.22269,
							39.06856
						],
						[
							111.21615,
							39.07061
						],
						[
							111.2101,
							39.07718
						],
						[
							111.20672,
							39.07885
						],
						[
							111.20162,
							39.09107
						],
						[
							111.19094,
							39.10684
						],
						[
							111.16558,
							39.11528
						],
						[
							111.17413,
							39.13516
						],
						[
							111.17394,
							39.13931
						],
						[
							111.1702,
							39.14439
						],
						[
							111.16424,
							39.14852
						],
						[
							111.16368,
							39.15405
						],
						[
							111.17472,
							39.1747
						],
						[
							111.18764,
							39.19006
						],
						[
							111.19601,
							39.2098
						],
						[
							111.20535,
							39.21966
						],
						[
							111.20401,
							39.22467
						],
						[
							111.21306,
							39.23078
						],
						[
							111.2173,
							39.23738
						],
						[
							111.219,
							39.24567
						],
						[
							111.21486,
							39.25077
						],
						[
							111.21344,
							39.25455
						],
						[
							111.21764,
							39.26939
						],
						[
							111.22395,
							39.2775
						],
						[
							111.22715,
							39.28438
						],
						[
							111.23092,
							39.28749
						],
						[
							111.24101,
							39.29229
						],
						[
							111.24805,
							39.30156
						],
						[
							111.24643,
							39.30254
						],
						[
							111.23465,
							39.30255
						],
						[
							111.2178,
							39.3008
						],
						[
							111.20768,
							39.30317
						],
						[
							111.19796,
							39.30729
						],
						[
							111.18797,
							39.31431
						],
						[
							111.18199,
							39.32135
						],
						[
							111.17943,
							39.32677
						],
						[
							111.18107,
							39.33178
						],
						[
							111.19421,
							39.34051
						],
						[
							111.19504,
							39.34498
						],
						[
							111.19139,
							39.34935
						],
						[
							111.18845,
							39.35089
						],
						[
							111.18365,
							39.3509
						],
						[
							111.17278,
							39.34607
						],
						[
							111.16951,
							39.34317
						],
						[
							111.1675,
							39.33725
						],
						[
							111.16174,
							39.3355
						],
						[
							111.15538,
							39.33869
						],
						[
							111.15409,
							39.34176
						],
						[
							111.15915,
							39.35778
						],
						[
							111.1588,
							39.36238
						],
						[
							111.15503,
							39.36828
						],
						[
							111.14797,
							39.36947
						],
						[
							111.12558,
							39.36645
						],
						[
							111.12008,
							39.37
						],
						[
							111.11908,
							39.37361
						],
						[
							111.11959,
							39.37725
						],
						[
							111.12852,
							39.38624
						],
						[
							111.14314,
							39.40779
						],
						[
							111.16137,
							39.415
						],
						[
							111.17435,
							39.4241
						],
						[
							111.17993,
							39.42352
						],
						[
							111.18677,
							39.42085
						],
						[
							111.19338,
							39.42042
						],
						[
							111.2054,
							39.42205
						],
						[
							111.21495,
							39.42605
						],
						[
							111.21747,
							39.42566
						],
						[
							111.22464,
							39.42106
						],
						[
							111.24286,
							39.4191
						],
						[
							111.25498,
							39.42094
						],
						[
							111.26518,
							39.42459
						],
						[
							111.27938,
							39.42125
						],
						[
							111.28744,
							39.41721
						],
						[
							111.29115,
							39.41762
						],
						[
							111.29578,
							39.42027
						],
						[
							111.30876,
							39.42218
						],
						[
							111.32572,
							39.42056
						],
						[
							111.33721,
							39.42094
						],
						[
							111.35245,
							39.42673
						],
						[
							111.35847,
							39.43253
						],
						[
							111.36408,
							39.44636
						],
						[
							111.36455,
							39.45303
						]
					]
				]
			},
			"properties": {
				"name": "河曲县",
				"adcode": "140930",
				"telecode": "0350",
				"level": "district",
				"parent": {
					"name": "忻州市",
					"level": "city",
					"adcode": "140900",
					"center": {
						"crs": {
							"type": "name",
							"properties": {
								"name": "urn:ogc:def:crs:EPSG:6.3:4326"
							}
						},
						"type": "Point",
						"coordinates": [
							112.733538,
							38.41769
						]
					}
				},
				"center": {
					"lng": 111.146609,
					"lat": 39.381895
				}
			}
		}
	]
}