{
	"type": "FeatureCollection",
	"features": [
		{
			"type": "Feature",
			"geometry": {
				"type": "Polygon",
				"coordinates": [
					[
						[
							118.08397,
							31.85382
						],
						[
							118.08671,
							31.85322
						],
						[
							118.08351,
							31.84603
						],
						[
							118.08362,
							31.84271
						],
						[
							118.08561,
							31.83915
						],
						[
							118.09651,
							31.83124
						],
						[
							118.11043,
							31.82413
						],
						[
							118.12575,
							31.82633
						],
						[
							118.13159,
							31.82369
						],
						[
							118.13684,
							31.81924
						],
						[
							118.14033,
							31.81871
						],
						[
							118.15491,
							31.82277
						],
						[
							118.16025,
							31.82174
						],
						[
							118.15903,
							31.81604
						],
						[
							118.14854,
							31.80457
						],
						[
							118.14791,
							31.80092
						],
						[
							118.14919,
							31.79814
						],
						[
							118.15207,
							31.79556
						],
						[
							118.17142,
							31.79723
						],
						[
							118.17773,
							31.79251
						],
						[
							118.17951,
							31.78858
						],
						[
							118.17963,
							31.78286
						],
						[
							118.17816,
							31.77807
						],
						[
							118.17875,
							31.77004
						],
						[
							118.18305,
							31.75627
						],
						[
							118.16935,
							31.73839
						],
						[
							118.16498,
							31.72686
						],
						[
							118.16462,
							31.71999
						],
						[
							118.16611,
							31.71307
						],
						[
							118.17635,
							31.70917
						],
						[
							118.20035,
							31.71803
						],
						[
							118.21697,
							31.7222
						],
						[
							118.22175,
							31.71825
						],
						[
							118.22492,
							31.71319
						],
						[
							118.22424,
							31.71131
						],
						[
							118.21858,
							31.70683
						],
						[
							118.21011,
							31.70219
						],
						[
							118.20381,
							31.70059
						],
						[
							118.19613,
							31.69383
						],
						[
							118.1957,
							31.69005
						],
						[
							118.19928,
							31.68384
						],
						[
							118.19881,
							31.6759
						],
						[
							118.19707,
							31.67066
						],
						[
							118.19015,
							31.66233
						],
						[
							118.1762,
							31.65139
						],
						[
							118.17476,
							31.64729
						],
						[
							118.17895,
							31.63346
						],
						[
							118.17851,
							31.62659
						],
						[
							118.17306,
							31.6228
						],
						[
							118.15761,
							31.61556
						],
						[
							118.15404,
							31.61197
						],
						[
							118.15194,
							31.60307
						],
						[
							118.15186,
							31.58955
						],
						[
							118.14966,
							31.57676
						],
						[
							118.15112,
							31.56068
						],
						[
							118.15035,
							31.5513
						],
						[
							118.1464,
							31.54336
						],
						[
							118.13845,
							31.53618
						],
						[
							118.13902,
							31.52011
						],
						[
							118.13445,
							31.51587
						],
						[
							118.13614,
							31.50053
						],
						[
							118.14154,
							31.49255
						],
						[
							118.14224,
							31.48394
						],
						[
							118.14492,
							31.47735
						],
						[
							118.15117,
							31.47453
						],
						[
							118.14975,
							31.47289
						],
						[
							118.15131,
							31.47001
						],
						[
							118.15044,
							31.46823
						],
						[
							118.14618,
							31.46988
						],
						[
							118.14577,
							31.46732
						],
						[
							118.14257,
							31.46924
						],
						[
							118.14278,
							31.47141
						],
						[
							118.1415,
							31.47174
						],
						[
							118.12815,
							31.46196
						],
						[
							118.12879,
							31.45912
						],
						[
							118.12742,
							31.45366
						],
						[
							118.12963,
							31.44887
						],
						[
							118.12879,
							31.442
						],
						[
							118.12975,
							31.43915
						],
						[
							118.13276,
							31.43683
						],
						[
							118.14924,
							31.43696
						],
						[
							118.15879,
							31.43333
						],
						[
							118.16497,
							31.43321
						],
						[
							118.16683,
							31.43082
						],
						[
							118.17121,
							31.43009
						],
						[
							118.16269,
							31.41377
						],
						[
							118.1641,
							31.40837
						],
						[
							118.16861,
							31.4034
						],
						[
							118.16852,
							31.40185
						],
						[
							118.16515,
							31.39914
						],
						[
							118.14899,
							31.40001
						],
						[
							118.08526,
							31.41418
						],
						[
							118.0799,
							31.41493
						],
						[
							118.07423,
							31.41344
						],
						[
							118.07267,
							31.41531
						],
						[
							118.0649,
							31.41547
						],
						[
							118.04919,
							31.41923
						],
						[
							118.039,
							31.41943
						],
						[
							117.99999,
							31.43534
						],
						[
							117.9738,
							31.44092
						],
						[
							117.97384,
							31.44596
						],
						[
							117.97082,
							31.45365
						],
						[
							117.96651,
							31.45796
						],
						[
							117.96281,
							31.46476
						],
						[
							117.98027,
							31.4668
						],
						[
							117.98847,
							31.47195
						],
						[
							117.98691,
							31.4745
						],
						[
							117.97845,
							31.48035
						],
						[
							117.96484,
							31.48399
						],
						[
							117.96302,
							31.48654
						],
						[
							117.96576,
							31.50383
						],
						[
							117.95825,
							31.5074
						],
						[
							117.95463,
							31.51853
						],
						[
							117.94182,
							31.52209
						],
						[
							117.93971,
							31.52398
						],
						[
							117.93955,
							31.52509
						],
						[
							117.94503,
							31.52872
						],
						[
							117.95087,
							31.5352
						],
						[
							117.95196,
							31.53863
						],
						[
							117.95104,
							31.53989
						],
						[
							117.94165,
							31.54065
						],
						[
							117.93018,
							31.53758
						],
						[
							117.92805,
							31.53842
						],
						[
							117.9198,
							31.54924
						],
						[
							117.91681,
							31.55013
						],
						[
							117.90829,
							31.54687
						],
						[
							117.90734,
							31.54908
						],
						[
							117.90866,
							31.5526
						],
						[
							117.90745,
							31.5576
						],
						[
							117.91397,
							31.56059
						],
						[
							117.91428,
							31.56543
						],
						[
							117.91906,
							31.56731
						],
						[
							117.92825,
							31.56823
						],
						[
							117.93019,
							31.57355
						],
						[
							117.93541,
							31.57851
						],
						[
							117.93495,
							31.58097
						],
						[
							117.93182,
							31.58066
						],
						[
							117.93015,
							31.58178
						],
						[
							117.92931,
							31.58571
						],
						[
							117.92991,
							31.58755
						],
						[
							117.9347,
							31.58689
						],
						[
							117.93624,
							31.58988
						],
						[
							117.93538,
							31.5986
						],
						[
							117.93184,
							31.60568
						],
						[
							117.93282,
							31.60795
						],
						[
							117.93719,
							31.61046
						],
						[
							117.93461,
							31.61812
						],
						[
							117.93862,
							31.62603
						],
						[
							117.93924,
							31.63209
						],
						[
							117.93896,
							31.63516
						],
						[
							117.93473,
							31.63702
						],
						[
							117.93019,
							31.64306
						],
						[
							117.92969,
							31.64872
						],
						[
							117.93087,
							31.65708
						],
						[
							117.93602,
							31.66675
						],
						[
							117.94114,
							31.67309
						],
						[
							117.94217,
							31.67727
						],
						[
							117.94144,
							31.67905
						],
						[
							117.93414,
							31.68084
						],
						[
							117.92798,
							31.68533
						],
						[
							117.92258,
							31.69329
						],
						[
							117.91583,
							31.69871
						],
						[
							117.91322,
							31.70405
						],
						[
							117.91308,
							31.71536
						],
						[
							117.91863,
							31.72356
						],
						[
							117.92,
							31.72831
						],
						[
							117.92006,
							31.73415
						],
						[
							117.91833,
							31.74164
						],
						[
							117.91565,
							31.74442
						],
						[
							117.91528,
							31.75032
						],
						[
							117.91629,
							31.75307
						],
						[
							117.92369,
							31.75802
						],
						[
							117.92512,
							31.7603
						],
						[
							117.92164,
							31.76329
						],
						[
							117.90946,
							31.76744
						],
						[
							117.90579,
							31.77094
						],
						[
							117.90504,
							31.77347
						],
						[
							117.90594,
							31.77758
						],
						[
							117.91343,
							31.78754
						],
						[
							117.90541,
							31.8005
						],
						[
							117.90137,
							31.81179
						],
						[
							117.90803,
							31.83253
						],
						[
							117.91083,
							31.83775
						],
						[
							117.91387,
							31.84091
						],
						[
							117.92803,
							31.84824
						],
						[
							117.93574,
							31.85545
						],
						[
							117.94316,
							31.87298
						],
						[
							117.94471,
							31.88166
						],
						[
							117.94963,
							31.89579
						],
						[
							117.94814,
							31.903
						],
						[
							117.95185,
							31.90624
						],
						[
							117.95481,
							31.90296
						],
						[
							117.96434,
							31.90155
						],
						[
							117.98881,
							31.88153
						],
						[
							118.04085,
							31.86089
						],
						[
							118.04482,
							31.85953
						],
						[
							118.06178,
							31.85854
						],
						[
							118.06897,
							31.85218
						],
						[
							118.07286,
							31.85093
						],
						[
							118.07948,
							31.85406
						],
						[
							118.08397,
							31.85382
						]
					]
				]
			},
			"properties": {
				"name": "含山县",
				"adcode": "340522",
				"telecode": "0555",
				"level": "district",
				"parent": {
					"name": "马鞍山市",
					"level": "city",
					"adcode": "340500",
					"center": {
						"crs": {
							"type": "name",
							"properties": {
								"name": "urn:ogc:def:crs:EPSG:6.3:4326"
							}
						},
						"type": "Point",
						"coordinates": [
							118.507906,
							31.689362
						]
					}
				},
				"center": {
					"lng": 118.105545,
					"lat": 31.727758
				}
			}
		}
	]
}