{
	"type": "FeatureCollection",
	"features": [
		{
			"type": "Feature",
			"geometry": {
				"type": "Polygon",
				"coordinates": [
					[
						[
							113.27639,
							31.34859
						],
						[
							113.29518,
							31.34097
						],
						[
							113.29684,
							31.33741
						],
						[
							113.29769,
							31.32757
						],
						[
							113.3003,
							31.32622
						],
						[
							113.30211,
							31.32693
						],
						[
							113.30424,
							31.3332
						],
						[
							113.31223,
							31.33602
						],
						[
							113.31668,
							31.34012
						],
						[
							113.32977,
							31.32733
						],
						[
							113.33166,
							31.323
						],
						[
							113.33042,
							31.31826
						],
						[
							113.33486,
							31.31648
						],
						[
							113.338,
							31.31797
						],
						[
							113.34344,
							31.31513
						],
						[
							113.34991,
							31.30416
						],
						[
							113.35328,
							31.30782
						],
						[
							113.35965,
							31.30723
						],
						[
							113.3626,
							31.30108
						],
						[
							113.36653,
							31.29812
						],
						[
							113.36618,
							31.29366
						],
						[
							113.36819,
							31.28552
						],
						[
							113.37351,
							31.2815
						],
						[
							113.37616,
							31.27576
						],
						[
							113.37705,
							31.27546
						],
						[
							113.38002,
							31.28504
						],
						[
							113.38542,
							31.29083
						],
						[
							113.38879,
							31.29193
						],
						[
							113.39272,
							31.28734
						],
						[
							113.3947,
							31.28693
						],
						[
							113.39735,
							31.28988
						],
						[
							113.40739,
							31.29095
						],
						[
							113.41161,
							31.2867
						],
						[
							113.41255,
							31.28302
						],
						[
							113.42304,
							31.28023
						],
						[
							113.42582,
							31.27464
						],
						[
							113.42985,
							31.25793
						],
						[
							113.43394,
							31.25441
						],
						[
							113.4375,
							31.25398
						],
						[
							113.44053,
							31.24252
						],
						[
							113.44473,
							31.23458
						],
						[
							113.45205,
							31.2309
						],
						[
							113.46174,
							31.23288
						],
						[
							113.48191,
							31.23036
						],
						[
							113.48734,
							31.22628
						],
						[
							113.49046,
							31.21217
						],
						[
							113.49138,
							31.15316
						],
						[
							113.48735,
							31.14308
						],
						[
							113.47702,
							31.13056
						],
						[
							113.47867,
							31.12739
						],
						[
							113.48344,
							31.12355
						],
						[
							113.49483,
							31.11709
						],
						[
							113.48817,
							31.11191
						],
						[
							113.48068,
							31.11309
						],
						[
							113.4778,
							31.10749
						],
						[
							113.46886,
							31.10405
						],
						[
							113.46962,
							31.0963
						],
						[
							113.46786,
							31.0929
						],
						[
							113.46788,
							31.08992
						],
						[
							113.46917,
							31.07037
						],
						[
							113.46603,
							31.05899
						],
						[
							113.45904,
							31.04522
						],
						[
							113.45347,
							31.03967
						],
						[
							113.43642,
							31.02714
						],
						[
							113.43111,
							31.02099
						],
						[
							113.4293,
							31.0136
						],
						[
							113.41859,
							31.00853
						],
						[
							113.41591,
							31.00451
						],
						[
							113.40879,
							31.00473
						],
						[
							113.40341,
							30.99913
						],
						[
							113.40332,
							30.99462
						],
						[
							113.39821,
							30.99092
						],
						[
							113.39523,
							30.98607
						],
						[
							113.39189,
							30.98595
						],
						[
							113.3859,
							30.99214
						],
						[
							113.38246,
							30.99383
						],
						[
							113.38181,
							30.99209
						],
						[
							113.3838,
							30.98297
						],
						[
							113.38653,
							30.98052
						],
						[
							113.38618,
							30.9743
						],
						[
							113.38683,
							30.97267
						],
						[
							113.38964,
							30.97188
						],
						[
							113.39198,
							30.96583
						],
						[
							113.37932,
							30.96685
						],
						[
							113.37514,
							30.96515
						],
						[
							113.37181,
							30.96626
						],
						[
							113.36623,
							30.95997
						],
						[
							113.36706,
							30.9565
						],
						[
							113.36417,
							30.95361
						],
						[
							113.36543,
							30.94773
						],
						[
							113.36191,
							30.94903
						],
						[
							113.35801,
							30.94519
						],
						[
							113.36185,
							30.93853
						],
						[
							113.36183,
							30.93538
						],
						[
							113.3648,
							30.93242
						],
						[
							113.36392,
							30.92991
						],
						[
							113.35794,
							30.92976
						],
						[
							113.35313,
							30.93211
						],
						[
							113.3466,
							30.9313
						],
						[
							113.34244,
							30.93844
						],
						[
							113.3392,
							30.93793
						],
						[
							113.33605,
							30.93622
						],
						[
							113.33527,
							30.93381
						],
						[
							113.3298,
							30.93214
						],
						[
							113.32895,
							30.93042
						],
						[
							113.33199,
							30.92594
						],
						[
							113.32915,
							30.92425
						],
						[
							113.32899,
							30.9211
						],
						[
							113.33106,
							30.9183
						],
						[
							113.33416,
							30.91818
						],
						[
							113.33438,
							30.91716
						],
						[
							113.33319,
							30.91514
						],
						[
							113.33367,
							30.9131
						],
						[
							113.33134,
							30.91331
						],
						[
							113.32817,
							30.91117
						],
						[
							113.3302,
							30.90074
						],
						[
							113.33,
							30.89467
						],
						[
							113.32621,
							30.88896
						],
						[
							113.31549,
							30.89169
						],
						[
							113.30232,
							30.89872
						],
						[
							113.29931,
							30.89528
						],
						[
							113.29693,
							30.89526
						],
						[
							113.29638,
							30.89834
						],
						[
							113.29237,
							30.90012
						],
						[
							113.2919,
							30.90332
						],
						[
							113.28734,
							30.90372
						],
						[
							113.28036,
							30.9018
						],
						[
							113.27036,
							30.89672
						],
						[
							113.26727,
							30.8915
						],
						[
							113.25816,
							30.88648
						],
						[
							113.2571,
							30.88033
						],
						[
							113.25043,
							30.8763
						],
						[
							113.245,
							30.86812
						],
						[
							113.24253,
							30.86694
						],
						[
							113.23458,
							30.8686
						],
						[
							113.23091,
							30.86773
						],
						[
							113.23081,
							30.86651
						],
						[
							113.23687,
							30.86225
						],
						[
							113.23756,
							30.8599
						],
						[
							113.23201,
							30.85375
						],
						[
							113.2287,
							30.85403
						],
						[
							113.22169,
							30.85873
						],
						[
							113.21961,
							30.85873
						],
						[
							113.21621,
							30.85519
						],
						[
							113.21708,
							30.85118
						],
						[
							113.21278,
							30.84444
						],
						[
							113.20178,
							30.83113
						],
						[
							113.19761,
							30.82411
						],
						[
							113.18862,
							30.81627
						],
						[
							113.1665,
							30.81194
						],
						[
							113.15841,
							30.80752
						],
						[
							113.14367,
							30.80233
						],
						[
							113.131,
							30.80489
						],
						[
							113.12397,
							30.80986
						],
						[
							113.09415,
							30.81712
						],
						[
							113.09079,
							30.82131
						],
						[
							113.08658,
							30.823
						],
						[
							113.07862,
							30.82361
						],
						[
							113.07643,
							30.82112
						],
						[
							113.07506,
							30.81035
						],
						[
							113.07894,
							30.79582
						],
						[
							113.07598,
							30.78508
						],
						[
							113.0727,
							30.78192
						],
						[
							113.06785,
							30.77994
						],
						[
							113.05159,
							30.77908
						],
						[
							113.03497,
							30.77568
						],
						[
							113.02414,
							30.77907
						],
						[
							113.01377,
							30.79003
						],
						[
							113.01058,
							30.791
						],
						[
							113.00037,
							30.78795
						],
						[
							112.99221,
							30.78188
						],
						[
							112.97869,
							30.76418
						],
						[
							112.96785,
							30.7577
						],
						[
							112.94712,
							30.74862
						],
						[
							112.93057,
							30.7365
						],
						[
							112.92132,
							30.71738
						],
						[
							112.91567,
							30.71495
						],
						[
							112.91006,
							30.71437
						],
						[
							112.89637,
							30.7173
						],
						[
							112.89133,
							30.71111
						],
						[
							112.89237,
							30.70018
						],
						[
							112.88948,
							30.69811
						],
						[
							112.88022,
							30.69776
						],
						[
							112.87411,
							30.70035
						],
						[
							112.87032,
							30.70591
						],
						[
							112.86806,
							30.70421
						],
						[
							112.8663,
							30.7045
						],
						[
							112.86297,
							30.70982
						],
						[
							112.84921,
							30.71614
						],
						[
							112.84779,
							30.72329
						],
						[
							112.84533,
							30.72561
						],
						[
							112.84252,
							30.72582
						],
						[
							112.84117,
							30.7293
						],
						[
							112.83093,
							30.72746
						],
						[
							112.82994,
							30.73042
						],
						[
							112.83489,
							30.73082
						],
						[
							112.83549,
							30.73184
						],
						[
							112.83024,
							30.73878
						],
						[
							112.83073,
							30.74037
						],
						[
							112.83328,
							30.74153
						],
						[
							112.83302,
							30.74286
						],
						[
							112.82822,
							30.7456
						],
						[
							112.83142,
							30.74702
						],
						[
							112.82806,
							30.75269
						],
						[
							112.8293,
							30.7562
						],
						[
							112.83029,
							30.75741
						],
						[
							112.83317,
							30.75683
						],
						[
							112.8342,
							30.75778
						],
						[
							112.8328,
							30.76226
						],
						[
							112.83314,
							30.76613
						],
						[
							112.82928,
							30.77283
						],
						[
							112.8324,
							30.77838
						],
						[
							112.83124,
							30.77983
						],
						[
							112.82696,
							30.78087
						],
						[
							112.82673,
							30.78544
						],
						[
							112.82071,
							30.78972
						],
						[
							112.8207,
							30.79399
						],
						[
							112.82352,
							30.80162
						],
						[
							112.81933,
							30.80559
						],
						[
							112.82074,
							30.80654
						],
						[
							112.82079,
							30.80844
						],
						[
							112.81694,
							30.81347
						],
						[
							112.8133,
							30.81408
						],
						[
							112.81172,
							30.81906
						],
						[
							112.81232,
							30.82292
						],
						[
							112.80212,
							30.82623
						],
						[
							112.79937,
							30.83032
						],
						[
							112.78749,
							30.84028
						],
						[
							112.78319,
							30.84144
						],
						[
							112.78388,
							30.84631
						],
						[
							112.76835,
							30.85914
						],
						[
							112.76842,
							30.86323
						],
						[
							112.76523,
							30.86894
						],
						[
							112.76704,
							30.88403
						],
						[
							112.76525,
							30.89074
						],
						[
							112.75407,
							30.90239
						],
						[
							112.75187,
							30.90636
						],
						[
							112.74996,
							30.92158
						],
						[
							112.74623,
							30.93295
						],
						[
							112.7386,
							30.94056
						],
						[
							112.72872,
							30.94617
						],
						[
							112.72835,
							30.9494
						],
						[
							112.72903,
							30.95236
						],
						[
							112.73474,
							30.95997
						],
						[
							112.73561,
							30.96682
						],
						[
							112.73888,
							30.9736
						],
						[
							112.74284,
							30.97805
						],
						[
							112.75367,
							30.99763
						],
						[
							112.75963,
							31.00477
						],
						[
							112.77799,
							31.01443
						],
						[
							112.78514,
							31.0245
						],
						[
							112.78871,
							31.02643
						],
						[
							112.79736,
							31.02887
						],
						[
							112.8106,
							31.027
						],
						[
							112.82152,
							31.0321
						],
						[
							112.83251,
							31.04373
						],
						[
							112.84741,
							31.05423
						],
						[
							112.85426,
							31.06282
						],
						[
							112.8579,
							31.07033
						],
						[
							112.85806,
							31.08732
						],
						[
							112.85986,
							31.09577
						],
						[
							112.85815,
							31.10109
						],
						[
							112.84876,
							31.10908
						],
						[
							112.84203,
							31.11679
						],
						[
							112.84178,
							31.12804
						],
						[
							112.87245,
							31.14145
						],
						[
							112.87294,
							31.14993
						],
						[
							112.87043,
							31.15595
						],
						[
							112.86952,
							31.16216
						],
						[
							112.87071,
							31.16696
						],
						[
							112.88047,
							31.17389
						],
						[
							112.89568,
							31.1743
						],
						[
							112.90371,
							31.17575
						],
						[
							112.90411,
							31.1909
						],
						[
							112.91001,
							31.20319
						],
						[
							112.93431,
							31.21332
						],
						[
							112.93492,
							31.21629
						],
						[
							112.93315,
							31.22046
						],
						[
							112.92385,
							31.22246
						],
						[
							112.91541,
							31.22628
						],
						[
							112.91283,
							31.22953
						],
						[
							112.91077,
							31.23302
						],
						[
							112.90587,
							31.24986
						],
						[
							112.89093,
							31.27148
						],
						[
							112.88737,
							31.28876
						],
						[
							112.88811,
							31.29724
						],
						[
							112.89184,
							31.30728
						],
						[
							112.89513,
							31.31088
						],
						[
							112.90489,
							31.31575
						],
						[
							112.93269,
							31.31618
						],
						[
							112.93466,
							31.31982
						],
						[
							112.93554,
							31.33358
						],
						[
							112.93978,
							31.34222
						],
						[
							112.96926,
							31.35299
						],
						[
							113.00275,
							31.3621
						],
						[
							113.00927,
							31.36498
						],
						[
							113.01204,
							31.36838
						],
						[
							113.01215,
							31.37205
						],
						[
							113.00979,
							31.37461
						],
						[
							112.99764,
							31.38145
						],
						[
							113.0043,
							31.38961
						],
						[
							113.00421,
							31.3965
						],
						[
							112.99375,
							31.41663
						],
						[
							112.99236,
							31.43332
						],
						[
							113.01635,
							31.44146
						],
						[
							113.02196,
							31.44728
						],
						[
							113.02634,
							31.44947
						],
						[
							113.03734,
							31.44851
						],
						[
							113.05543,
							31.43658
						],
						[
							113.06116,
							31.43873
						],
						[
							113.06807,
							31.44359
						],
						[
							113.07297,
							31.44507
						],
						[
							113.08027,
							31.44671
						],
						[
							113.09207,
							31.44594
						],
						[
							113.10293,
							31.44265
						],
						[
							113.11132,
							31.43462
						],
						[
							113.11168,
							31.42891
						],
						[
							113.11344,
							31.42664
						],
						[
							113.12243,
							31.42901
						],
						[
							113.12627,
							31.4259
						],
						[
							113.13261,
							31.42584
						],
						[
							113.14027,
							31.43141
						],
						[
							113.14354,
							31.43642
						],
						[
							113.14559,
							31.43753
						],
						[
							113.15212,
							31.43312
						],
						[
							113.15417,
							31.42878
						],
						[
							113.1613,
							31.42854
						],
						[
							113.16036,
							31.42424
						],
						[
							113.15442,
							31.42001
						],
						[
							113.15247,
							31.42063
						],
						[
							113.15035,
							31.42554
						],
						[
							113.14874,
							31.42644
						],
						[
							113.14736,
							31.42488
						],
						[
							113.14671,
							31.41817
						],
						[
							113.14787,
							31.41612
						],
						[
							113.15369,
							31.41451
						],
						[
							113.15905,
							31.4067
						],
						[
							113.16139,
							31.40574
						],
						[
							113.16425,
							31.40651
						],
						[
							113.16686,
							31.41112
						],
						[
							113.16939,
							31.41203
						],
						[
							113.2068,
							31.3955
						],
						[
							113.2229,
							31.3769
						],
						[
							113.22654,
							31.37426
						],
						[
							113.24048,
							31.3548
						],
						[
							113.24974,
							31.35866
						],
						[
							113.25456,
							31.35852
						],
						[
							113.26332,
							31.35689
						],
						[
							113.27639,
							31.34859
						]
					],
					[
						[
							112.82642,
							30.72292
						],
						[
							112.82504,
							30.72187
						],
						[
							112.8238,
							30.72321
						],
						[
							112.82578,
							30.72656
						],
						[
							112.82776,
							30.72731
						],
						[
							112.82898,
							30.72577
						],
						[
							112.82642,
							30.72292
						]
					]
				]
			},
			"properties": {
				"name": "京山县",
				"adcode": "420821",
				"telecode": "0724",
				"level": "district",
				"parent": {
					"name": "荆门市",
					"level": "city",
					"adcode": "420800",
					"center": {
						"crs": {
							"type": "name",
							"properties": {
								"name": "urn:ogc:def:crs:EPSG:6.3:4326"
							}
						},
						"type": "Point",
						"coordinates": [
							112.204251,
							31.03542
						]
					}
				},
				"center": {
					"lng": 113.114595,
					"lat": 31.022458
				}
			}
		}
	]
}