{
	"type": "FeatureCollection",
	"features": [
		{
			"type": "Feature",
			"geometry": {
				"type": "Polygon",
				"coordinates": [
					[
						[
							105.61868,
							30.97756
						],
						[
							105.61998,
							30.97336
						],
						[
							105.628,
							30.97362
						],
						[
							105.62939,
							30.96736
						],
						[
							105.63463,
							30.96333
						],
						[
							105.64347,
							30.94805
						],
						[
							105.64664,
							30.94491
						],
						[
							105.65988,
							30.94224
						],
						[
							105.65977,
							30.92771
						],
						[
							105.65684,
							30.92388
						],
						[
							105.65078,
							30.92592
						],
						[
							105.6444,
							30.92127
						],
						[
							105.63055,
							30.91802
						],
						[
							105.62503,
							30.91407
						],
						[
							105.612,
							30.91745
						],
						[
							105.61101,
							30.91279
						],
						[
							105.6074,
							30.90958
						],
						[
							105.60524,
							30.9028
						],
						[
							105.60293,
							30.90155
						],
						[
							105.59765,
							30.90432
						],
						[
							105.59651,
							30.88335
						],
						[
							105.58612,
							30.86475
						],
						[
							105.58645,
							30.85419
						],
						[
							105.57971,
							30.84961
						],
						[
							105.57923,
							30.84208
						],
						[
							105.57314,
							30.83732
						],
						[
							105.57204,
							30.82922
						],
						[
							105.57868,
							30.81961
						],
						[
							105.57408,
							30.81682
						],
						[
							105.57075,
							30.81689
						],
						[
							105.56537,
							30.82385
						],
						[
							105.56108,
							30.82509
						],
						[
							105.5568,
							30.82395
						],
						[
							105.55501,
							30.82
						],
						[
							105.56106,
							30.81735
						],
						[
							105.56462,
							30.81316
						],
						[
							105.5675,
							30.80787
						],
						[
							105.5669,
							30.80521
						],
						[
							105.5641,
							30.80341
						],
						[
							105.55859,
							30.80409
						],
						[
							105.555,
							30.8032
						],
						[
							105.55034,
							30.80494
						],
						[
							105.5474,
							30.80422
						],
						[
							105.54518,
							30.80314
						],
						[
							105.54262,
							30.7934
						],
						[
							105.53863,
							30.78878
						],
						[
							105.51756,
							30.78325
						],
						[
							105.51919,
							30.78134
						],
						[
							105.51794,
							30.77728
						],
						[
							105.51866,
							30.77527
						],
						[
							105.52238,
							30.76981
						],
						[
							105.52822,
							30.76489
						],
						[
							105.52274,
							30.75374
						],
						[
							105.51554,
							30.75449
						],
						[
							105.51338,
							30.75782
						],
						[
							105.5164,
							30.76389
						],
						[
							105.50962,
							30.76545
						],
						[
							105.50554,
							30.76308
						],
						[
							105.50756,
							30.75609
						],
						[
							105.50437,
							30.75063
						],
						[
							105.49309,
							30.74845
						],
						[
							105.48867,
							30.74179
						],
						[
							105.48212,
							30.74244
						],
						[
							105.48108,
							30.73762
						],
						[
							105.4769,
							30.73298
						],
						[
							105.47169,
							30.73137
						],
						[
							105.4651,
							30.73429
						],
						[
							105.45792,
							30.72822
						],
						[
							105.44064,
							30.72449
						],
						[
							105.44298,
							30.70907
						],
						[
							105.43655,
							30.69473
						],
						[
							105.43666,
							30.68901
						],
						[
							105.43388,
							30.68793
						],
						[
							105.42676,
							30.68823
						],
						[
							105.42681,
							30.68338
						],
						[
							105.41953,
							30.68192
						],
						[
							105.4133,
							30.67661
						],
						[
							105.40742,
							30.67829
						],
						[
							105.40441,
							30.68276
						],
						[
							105.40031,
							30.68233
						],
						[
							105.39805,
							30.68014
						],
						[
							105.398,
							30.67462
						],
						[
							105.39276,
							30.67228
						],
						[
							105.39407,
							30.66637
						],
						[
							105.39115,
							30.66442
						],
						[
							105.38949,
							30.66011
						],
						[
							105.38262,
							30.65891
						],
						[
							105.37504,
							30.66042
						],
						[
							105.36759,
							30.65804
						],
						[
							105.36794,
							30.65254
						],
						[
							105.3665,
							30.64674
						],
						[
							105.36937,
							30.64065
						],
						[
							105.3677,
							30.63822
						],
						[
							105.35202,
							30.63312
						],
						[
							105.35028,
							30.63535
						],
						[
							105.34892,
							30.64322
						],
						[
							105.35123,
							30.64776
						],
						[
							105.34916,
							30.65229
						],
						[
							105.34743,
							30.65273
						],
						[
							105.3452,
							30.65078
						],
						[
							105.33841,
							30.64899
						],
						[
							105.3367,
							30.6507
						],
						[
							105.33654,
							30.65388
						],
						[
							105.33139,
							30.65644
						],
						[
							105.32904,
							30.65626
						],
						[
							105.32795,
							30.65399
						],
						[
							105.32465,
							30.65229
						],
						[
							105.32135,
							30.65403
						],
						[
							105.31638,
							30.6539
						],
						[
							105.31172,
							30.66282
						],
						[
							105.30959,
							30.6645
						],
						[
							105.30396,
							30.66278
						],
						[
							105.30242,
							30.6646
						],
						[
							105.30217,
							30.66262
						],
						[
							105.29878,
							30.66239
						],
						[
							105.29199,
							30.66552
						],
						[
							105.28603,
							30.65962
						],
						[
							105.28187,
							30.66285
						],
						[
							105.28113,
							30.66533
						],
						[
							105.28388,
							30.66681
						],
						[
							105.28389,
							30.66906
						],
						[
							105.28678,
							30.67274
						],
						[
							105.28417,
							30.6757
						],
						[
							105.28562,
							30.67764
						],
						[
							105.28532,
							30.67995
						],
						[
							105.28785,
							30.68252
						],
						[
							105.2861,
							30.68619
						],
						[
							105.28766,
							30.68808
						],
						[
							105.29056,
							30.68768
						],
						[
							105.29442,
							30.68924
						],
						[
							105.29584,
							30.6982
						],
						[
							105.29212,
							30.69926
						],
						[
							105.28783,
							30.69836
						],
						[
							105.28415,
							30.70007
						],
						[
							105.28329,
							30.70178
						],
						[
							105.27935,
							30.70182
						],
						[
							105.27113,
							30.70745
						],
						[
							105.26774,
							30.70694
						],
						[
							105.26389,
							30.68971
						],
						[
							105.2596,
							30.68764
						],
						[
							105.25802,
							30.68169
						],
						[
							105.2545,
							30.68004
						],
						[
							105.24878,
							30.67121
						],
						[
							105.2466,
							30.67005
						],
						[
							105.2454,
							30.67209
						],
						[
							105.2461,
							30.66816
						],
						[
							105.24457,
							30.66727
						],
						[
							105.24118,
							30.66734
						],
						[
							105.23826,
							30.66999
						],
						[
							105.23506,
							30.66986
						],
						[
							105.22467,
							30.67421
						],
						[
							105.22208,
							30.67692
						],
						[
							105.22225,
							30.68008
						],
						[
							105.21944,
							30.68251
						],
						[
							105.21796,
							30.68144
						],
						[
							105.21646,
							30.67578
						],
						[
							105.21406,
							30.67567
						],
						[
							105.21307,
							30.6889
						],
						[
							105.20418,
							30.68932
						],
						[
							105.20211,
							30.68793
						],
						[
							105.20096,
							30.68894
						],
						[
							105.20235,
							30.6903
						],
						[
							105.20262,
							30.69498
						],
						[
							105.19841,
							30.69959
						],
						[
							105.19996,
							30.70387
						],
						[
							105.20625,
							30.70802
						],
						[
							105.20686,
							30.71269
						],
						[
							105.20984,
							30.71799
						],
						[
							105.20943,
							30.72271
						],
						[
							105.21107,
							30.72725
						],
						[
							105.21375,
							30.72644
						],
						[
							105.2203,
							30.72767
						],
						[
							105.21495,
							30.73332
						],
						[
							105.21521,
							30.73468
						],
						[
							105.2222,
							30.73202
						],
						[
							105.23033,
							30.73126
						],
						[
							105.24067,
							30.72646
						],
						[
							105.24403,
							30.72611
						],
						[
							105.2452,
							30.73388
						],
						[
							105.24863,
							30.73919
						],
						[
							105.25598,
							30.7436
						],
						[
							105.26273,
							30.74173
						],
						[
							105.26612,
							30.74665
						],
						[
							105.27102,
							30.75003
						],
						[
							105.27257,
							30.75352
						],
						[
							105.26702,
							30.75943
						],
						[
							105.27017,
							30.76677
						],
						[
							105.26586,
							30.77565
						],
						[
							105.26873,
							30.79127
						],
						[
							105.26382,
							30.80048
						],
						[
							105.26044,
							30.82288
						],
						[
							105.25495,
							30.83136
						],
						[
							105.24413,
							30.8314
						],
						[
							105.23957,
							30.83877
						],
						[
							105.2323,
							30.84627
						],
						[
							105.23025,
							30.85292
						],
						[
							105.23182,
							30.86385
						],
						[
							105.22985,
							30.86627
						],
						[
							105.23067,
							30.86878
						],
						[
							105.22867,
							30.87738
						],
						[
							105.22251,
							30.8791
						],
						[
							105.22263,
							30.88348
						],
						[
							105.22115,
							30.88509
						],
						[
							105.21854,
							30.88393
						],
						[
							105.21551,
							30.87894
						],
						[
							105.2099,
							30.88452
						],
						[
							105.20614,
							30.88226
						],
						[
							105.20402,
							30.88275
						],
						[
							105.20015,
							30.88619
						],
						[
							105.19469,
							30.89421
						],
						[
							105.19424,
							30.89697
						],
						[
							105.2055,
							30.90298
						],
						[
							105.20883,
							30.90617
						],
						[
							105.20922,
							30.9094
						],
						[
							105.20677,
							30.91288
						],
						[
							105.19448,
							30.91707
						],
						[
							105.19381,
							30.92295
						],
						[
							105.19141,
							30.9256
						],
						[
							105.19368,
							30.92839
						],
						[
							105.19298,
							30.93199
						],
						[
							105.18103,
							30.94805
						],
						[
							105.17737,
							30.95702
						],
						[
							105.17736,
							30.96018
						],
						[
							105.17998,
							30.96298
						],
						[
							105.18327,
							30.96415
						],
						[
							105.19116,
							30.96309
						],
						[
							105.1946,
							30.96557
						],
						[
							105.1938,
							30.97505
						],
						[
							105.19525,
							30.98057
						],
						[
							105.19468,
							30.99207
						],
						[
							105.18922,
							30.99779
						],
						[
							105.18623,
							31.0086
						],
						[
							105.18692,
							31.01648
						],
						[
							105.18192,
							31.02295
						],
						[
							105.18079,
							31.03067
						],
						[
							105.17554,
							31.03275
						],
						[
							105.1743,
							31.03439
						],
						[
							105.17601,
							31.03992
						],
						[
							105.17472,
							31.04598
						],
						[
							105.17671,
							31.04837
						],
						[
							105.18815,
							31.05309
						],
						[
							105.19421,
							31.06254
						],
						[
							105.19992,
							31.07795
						],
						[
							105.19924,
							31.08103
						],
						[
							105.19268,
							31.08762
						],
						[
							105.19394,
							31.09034
						],
						[
							105.197,
							31.09269
						],
						[
							105.19835,
							31.09655
						],
						[
							105.20785,
							31.09483
						],
						[
							105.21156,
							31.09581
						],
						[
							105.21778,
							31.10458
						],
						[
							105.22395,
							31.10767
						],
						[
							105.22838,
							31.10476
						],
						[
							105.23766,
							31.10454
						],
						[
							105.24048,
							31.10175
						],
						[
							105.24723,
							31.10443
						],
						[
							105.2591,
							31.10151
						],
						[
							105.26617,
							31.10158
						],
						[
							105.27943,
							31.10781
						],
						[
							105.28446,
							31.10418
						],
						[
							105.29167,
							31.10409
						],
						[
							105.29689,
							31.10632
						],
						[
							105.30093,
							31.11271
						],
						[
							105.3059,
							31.1116
						],
						[
							105.30937,
							31.11471
						],
						[
							105.31667,
							31.114
						],
						[
							105.32451,
							31.118
						],
						[
							105.32474,
							31.12213
						],
						[
							105.31946,
							31.12764
						],
						[
							105.32356,
							31.13712
						],
						[
							105.32591,
							31.13929
						],
						[
							105.32753,
							31.13858
						],
						[
							105.32977,
							31.12968
						],
						[
							105.33947,
							31.12615
						],
						[
							105.34443,
							31.12591
						],
						[
							105.34555,
							31.12897
						],
						[
							105.34211,
							31.13274
						],
						[
							105.34212,
							31.13772
						],
						[
							105.34804,
							31.14707
						],
						[
							105.35169,
							31.15018
						],
						[
							105.35398,
							31.1606
						],
						[
							105.3717,
							31.15757
						],
						[
							105.37398,
							31.15417
						],
						[
							105.37897,
							31.15479
						],
						[
							105.38129,
							31.15288
						],
						[
							105.3826,
							31.14614
						],
						[
							105.38024,
							31.14168
						],
						[
							105.38007,
							31.13813
						],
						[
							105.38173,
							31.133
						],
						[
							105.38967,
							31.12484
						],
						[
							105.38844,
							31.12075
						],
						[
							105.38861,
							31.1137
						],
						[
							105.39552,
							31.10707
						],
						[
							105.39737,
							31.09976
						],
						[
							105.4025,
							31.09734
						],
						[
							105.40274,
							31.0931
						],
						[
							105.40825,
							31.0885
						],
						[
							105.41079,
							31.08017
						],
						[
							105.40944,
							31.07557
						],
						[
							105.41077,
							31.07255
						],
						[
							105.41505,
							31.07182
						],
						[
							105.42333,
							31.07672
						],
						[
							105.42673,
							31.07649
						],
						[
							105.4293,
							31.07464
						],
						[
							105.43174,
							31.06781
						],
						[
							105.43397,
							31.0663
						],
						[
							105.44499,
							31.06688
						],
						[
							105.45521,
							31.05976
						],
						[
							105.46308,
							31.06341
						],
						[
							105.47471,
							31.06365
						],
						[
							105.47558,
							31.06069
						],
						[
							105.4792,
							31.05662
						],
						[
							105.48185,
							31.04565
						],
						[
							105.48885,
							31.03618
						],
						[
							105.49583,
							31.03852
						],
						[
							105.50536,
							31.03659
						],
						[
							105.50613,
							31.03499
						],
						[
							105.50449,
							31.02648
						],
						[
							105.51125,
							31.02663
						],
						[
							105.51578,
							31.02516
						],
						[
							105.52092,
							31.02707
						],
						[
							105.52612,
							31.02611
						],
						[
							105.53439,
							31.02703
						],
						[
							105.53768,
							31.02552
						],
						[
							105.5397,
							31.02143
						],
						[
							105.54544,
							31.01744
						],
						[
							105.54605,
							31.01361
						],
						[
							105.55806,
							31.00989
						],
						[
							105.56588,
							31.01121
						],
						[
							105.56529,
							31.00633
						],
						[
							105.56696,
							31.00017
						],
						[
							105.57218,
							30.99011
						],
						[
							105.57762,
							30.98642
						],
						[
							105.58549,
							30.98357
						],
						[
							105.5958,
							30.97258
						],
						[
							105.60227,
							30.9753
						],
						[
							105.61868,
							30.97756
						]
					]
				]
			},
			"properties": {
				"name": "射洪县",
				"adcode": "510922",
				"telecode": "0825",
				"level": "district",
				"parent": {
					"name": "遂宁市",
					"level": "city",
					"adcode": "510900",
					"center": {
						"crs": {
							"type": "name",
							"properties": {
								"name": "urn:ogc:def:crs:EPSG:6.3:4326"
							}
						},
						"type": "Point",
						"coordinates": [
							105.571331,
							30.513311
						]
					}
				},
				"center": {
					"lng": 105.381849,
					"lat": 30.868752
				}
			}
		}
	]
}